battkit/.DS_Store
battkit/__init__.py
battkit/config.py
battkit/logging_config.py
battkit/data/__init__.py
battkit/data/__pycache__/__init__.cpython-312.pyc
battkit/data/data_converter/__init__.py
battkit/data/data_converter/base.py
battkit/data/data_converter/neware.py
battkit/data/data_converter/__pycache__/__init__.cpython-312.pyc
battkit/data/data_converter/__pycache__/base.cpython-312.pyc
battkit/data/data_converter/__pycache__/neware.cpython-312.pyc
battkit/data/dataset/__init__.py
battkit/data/dataset/dataset.py
battkit/data/dataset/table_manager.py
battkit/data/dataset/utils.py
battkit/data/dataset/__pycache__/__init__.cpython-312.pyc
battkit/data/dataset/__pycache__/dataset.cpython-312.pyc
battkit/data/dataset/__pycache__/table_manager.cpython-312.pyc
battkit/data/dataset/__pycache__/utils.cpython-312.pyc
battkit/data/test_schema/__init__.py
battkit/data/test_schema/base.py
battkit/data/test_schema/frequency.py
battkit/data/test_schema/time_series.py
battkit/data/test_schema/__pycache__/__init__.cpython-310.pyc
battkit/data/test_schema/__pycache__/__init__.cpython-312.pyc
battkit/data/test_schema/__pycache__/base.cpython-312.pyc
battkit/data/test_schema/__pycache__/time_series.cpython-312.pyc
battkit/utils/__init__.py
battkit/utils/dataframe_utils.py
battkit/utils/feature_utils.py
battkit/utils/file_utils.py
battkit/utils/typing_utils.py
battkit-0.0.16.dist-info/licenses/LICENSE
battkit-0.0.16.dist-info/METADATA
battkit-0.0.16.dist-info/WHEEL
battkit-0.0.16.dist-info/top_level.txt
battkit-0.0.16.dist-info/RECORD
