Metadata-Version: 2.4
Name: battkit
Version: 0.0.16
Summary: A tool kit for battery data preprocessing, standardization, and feature engineering
Author-email: Benjamin Nowacki <benjamin.nowacki@uconn.edu>, Tingkai Li <tingkai.li@uconn.edu>, Chao Hu <chao.hu@uconn.edu>
License-Expression: Apache-2.0
Project-URL: Homepage, https://github.com/REIL-UConn/battkit
Project-URL: Repository, https://github.com/REIL-UConn/battkit
Project-URL: Issues, https://github.com/REIL-UConn/battkit/issues
Keywords: battery data preprocessing,battery data standardization,feature engineering
Classifier: Development Status :: 3 - Alpha
Classifier: Intended Audience :: Science/Research
Classifier: Topic :: Scientific/Engineering
Classifier: Programming Language :: Python
Requires-Python: >=3.9
License-File: LICENSE
Requires-Dist: pandas>=2.2.3
Requires-Dist: numpy>=1.26.4
Requires-Dist: dask>=2024.5.0
Requires-Dist: xmltodict>=0.14.2
Requires-Dist: sxl>=0.0.1a10
Requires-Dist: pyarrow>=19.0.0
Requires-Dist: openpyxl>=3.1.5
Requires-Dist: newarenda>=2025.4.2
Requires-Dist: tqdm>=4.67.1
Dynamic: license-file
